{
    "ln":
        {
            "ick":1,
            "saki":2,
            "hnm":3,
            "shino":4
        },
    "mmj":
        {
            "mnr":5,
            "hrk":6,
            "airi":7,
            "szk":8
        },
    "vbs":
        {
            "khn":9,
            "an":10,
            "akt":11,
            "toya":12
        },
    "ws":               
        {
            "tks":13,
            "emu":14,
            "nene":15,
            "rui":16
        },
    "25h":
        {
            "knd":17,
            "mfy":18,
            "ena":19,
            "mzk":20
        },
    "vs":
        {
            "miku":21,
            "rin":22,
            "ren":23,
            "ruka":24,
            "meiko":25,
            "kaito":26      
        }
}